[{"sourceParam":{"eClass":"http://BfR/bund/de/knime/model/metadata_V1.0.3#//Parameter","parameterID":"SecondModelOutput_dup_dup","parameterClassification":"Output","parameterName":"SecondModelOutput_dup_dup","parameterDataType":"Integer","parameterValue":""},"targetParam":{"eClass":"http://BfR/bund/de/knime/model/metadata_V1.0.3#//Parameter","parameterID":"FirstModelInput_dup","parameterClassification":"Input","parameterName":"FirstModelInput_dup","parameterDataType":"Integer","parameterValue":"10"},"command":"SecondModelOutput_dup_dup * 2","language_written_in":"R 3"}]